wiki2md/__init__.py
wiki2md/__main__.py
wiki2md/html2md.py
wiki2md/py.typed
wiki2md-0.1.3.dist-info/LICENSE
wiki2md-0.1.3.dist-info/METADATA
wiki2md-0.1.3.dist-info/WHEEL
wiki2md-0.1.3.dist-info/entry_points.txt
wiki2md-0.1.3.dist-info/RECORD
